Detectify/__init__.py
Detectify/logger.py
Detectify/predict.py
Detectify/train.py
Detectify/util.py
detectify_python-1.0.6.dist-info/LICENSE
detectify_python-1.0.6.dist-info/METADATA
detectify_python-1.0.6.dist-info/WHEEL
detectify_python-1.0.6.dist-info/top_level.txt
detectify_python-1.0.6.dist-info/RECORD
