Metadata-Version: 2.1
Name: detectify-python
Version: 1.0.6
Summary: Detectify - YOLOv11 based object detection framework
Home-page: https://github.com/BackGwa/Detectify
Author: KANG CHANYOUNG
Author-email: backgwa@icloud.com
Requires-Python: >=3.9.0
License-File: LICENSE
Requires-Dist: ultralytics==8.3.13
